LICENSE
README.md
setup.py
aebin/__init__.py
aebin/main.py
aebin.egg-info/PKG-INFO
aebin.egg-info/SOURCES.txt
aebin.egg-info/dependency_links.txt
aebin.egg-info/top_level.txt