Metadata-Version: 2.1
Name: aebin
Version: 0.0.1
Summary: A binary file format for storing dictionaries.
Home-page: https://github.com/Aermoss/Aerics
Author: Yusuf Rencber
Author-email: yusufrencber546@gmail.com
License: MIT
Platform: UNKNOWN
License-File: LICENSE
